fermioniq/__init__.py
fermioniq/api.py
fermioniq/client.py
fermioniq/config/__init__.py
fermioniq/config/defaults.py
fermioniq/custom_logging/__init__.py
fermioniq/custom_logging/jobs_table_functions.py
fermioniq/custom_logging/printing.py
fermioniq/emulator_job.py
fermioniq/emulator_message.py
fermioniq/py.typed
fermioniq/test_utils/__init__.py
fermioniq/test_utils/mock_api.py
fermioniq/test_utils/mock_client.py
fermioniq/version.py
fermioniq-1.5.2.dist-info/LICENSE
fermioniq-1.5.2.dist-info/METADATA
fermioniq-1.5.2.dist-info/WHEEL
fermioniq-1.5.2.dist-info/RECORD
