Metadata-Version: 2.1
Name: fermioniq
Version: 1.5.2
Summary: Fermioniq client
License: MIT
Author: Fermioniq
Author-email: support@fermioniq.com
Requires-Python: >=3.10,<4.0
Classifier: License :: OSI Approved :: MIT License
Classifier: Programming Language :: Python :: 3
Classifier: Programming Language :: Python :: 3.10
Classifier: Programming Language :: Python :: 3.11
Classifier: Programming Language :: Python :: 3.12
Requires-Dist: fermioniq-qc (==1.5.2)
Requires-Dist: numpy (>=1.23.5,<2.0.0)
Requires-Dist: pydantic (>=2.8.2,<3.0.0)
Requires-Dist: pyyaml (>=6.0.1,<7.0.0)
Requires-Dist: requests (>=2.31.0,<3.0.0)
Requires-Dist: rich (>=13.5.2,<14.0.0)
Requires-Dist: websockets (>=10.0,<11.0)
Project-URL: Documentation, https://docs.fermioniq.com
